[
  {
    "key": 1817153241,
    "title": {
      "fa_IR": "روز شعر و ادب فارسی"
    },
    "description": {
      "fa_IR": "روز شعر و ادب فارسی"
    },
    "month": 6,
    "day": 27,
    "calendar": [
      "Iran Official"
    ],
    "sources": [
      "https://fa.wikipedia.org/wiki/روز_ملی_شعر_و_ادب"
    ]
  },
  {
    "key": 4124978417,
    "title": {
      "fa_IR": "روز بزرگداشت استاد سید محمدحسین شهریار"
    },
    "description": {
      "fa_IR": "روز بزرگداشت استاد سید محمدحسین شهریار"
    },
    "month": 6,
    "day": 27,
    "calendar": [
      "Iran Official"
    ],
    "sources": [
      "https://fa.wikipedia.org/wiki/سید_محمدحسین_شهریار"
    ]
  }
]